mvgcli/__init__.py
mvgcli/cli.py
mvgcli/command_line.py
mvgcli/config.py
mvgcli/defaults.py
mvgcli/departures_request.py
mvgcli/favorites.py
mvgcli/next_departures.py
mvg_cli-1.0.0.dist-info/LICENSE
mvg_cli-1.0.0.dist-info/METADATA
mvg_cli-1.0.0.dist-info/WHEEL
mvg_cli-1.0.0.dist-info/entry_points.txt
mvg_cli-1.0.0.dist-info/top_level.txt
mvg_cli-1.0.0.dist-info/RECORD
