Metadata-Version: 2.1
Name: mvg-cli
Version: 1.0.0
Summary: A CLI tool to get quick access to live MVG data from the command line.
Home-page: https://github.com/FlorianPfisterer/mvg-cli
Author: Florian Pfisterer
Author-email: florian@pfisterer.dev
License: UNKNOWN
Platform: UNKNOWN
Requires-Python: >=3.5
License-File: LICENSE
Requires-Dist: mvg-api (==1.2.7)
